{
  "scaleOrbits": true,
  "constrainOrbits": true,
  "keepStarCatalog": true,
  "fillPhotometry": true,
  "explainFiltering": true,
  "filterBinaries": false,
    "promote_hz_stars": true,
    "earths_only": false,
  "filter_for_char": true,
  "use_char_minintime": true,
    "lucky_planets": true,
    "find_known_RV": false,
  "max_successful_chars": 1,
  "max_successful_dets": 4,
  "ppFact": 0.29,
  "ppFact_char": 0.1,
  "stabilityFact": 0.1,
  "arange":[0.09, 12.4],
  "Rprange":[0.5, 11.6],
  "eta": 0.243731,

  "coeffs": [0.12,0,0.5,0,0.3,0,0.05],
  "settlingTime": 0.042,
  "thrust": 1200,
  "slewIsp": 2800,
  "scMass": 11180,
  "dryMass": 4550,
  "coMass":5800,
  "occulterSep":76600,
  "skIsp": 308,
  "defburnPortion":0.85,


 "modules": {
 "PlanetPopulation": "KeplerLike1",
 "StarCatalog": "EXOCAT1",
 "OpticalSystem": "Nemati",
 "ZodiacalLight": "Mennesson",
 "BackgroundSources": "GalaxiesFaintStars",
 "PlanetPhysicalModel": "Forecaster",
 "Observatory": "WFIRSTObservatoryL2",
 "TimeKeeping": " ",
 "PostProcessing": " ",
 "Completeness": "BrownCompleteness",
 "TargetList": " ",
 "SimulatedUniverse": "KeplerLikeUniverse",
 "SurveySimulation": " ",
 "SurveyEnsemble": " "
 },
 "scienceInstruments": [
 { "name": "imager" },
 { "name": "spectrometer" }
 ],
  "starlightSuppressionSystems": [
 {  "name": "coronagraph",
    "IWA": 0.070,
    "OWA": 1.0,
    "core_contrast": 2.5e-11
 }
  ],
  "pupilDiam": 6.0,
  "obscurFac": 0.0,
  "ppFact": 0.1,
  "observingModes": [
    { "instName": "imager",
      "systName": "coronagraph",
      "detectionMode": true,
      "SNR": 7
    },
    { "instName": "spectrometer",
      "systName": "coronagraph",
      "SNR": 10
    }
 ],
 "minComp": 0.01,
 "dMagLim": 31.0,
 "missionLife": 5,
 "missionPortion": 0.4}